{
  "ts": 1777506899.7322197,
  "version": "v12.9v_deepened_visual_judge",
  "status": "ranking_emitted",
  "latest_entry_sha256": "1d5777bd0ce8cbca",
  "latest_spec_sha256": "159b89c23765644c",
  "latest_depth": 243,
  "latest_svg": "static/generated/leveon_topology_1777506898_9b15631162df.svg",
  "latest_metrics": {
    "topology_score": 0.9032,
    "chamber_memory": 0.8,
    "has_svg": true,
    "has_depth": true,
    "has_core": true,
    "has_render_logic": true,
    "symbol_presence": {
      "white_ash": true,
      "virellion": true,
      "blue_scarf": true,
      "thalveil": true,
      "liquid_core": true,
      "echoforge": true
    },
    "symbol_strength": 6,
    "symbol_coverage": 1.0,
    "white_ash_containment_efficiency": 1.0,
    "virellion_thread_integrity": 1.0,
    "blue_scarf_motion_velocity": 0.8372,
    "thalveil_crossing_clarity": 1.0,
    "echoforge_painting_fidelity": 1.0,
    "liquid_core_routing_purity": 1.0,
    "overall_organ_coherence": 0.9456,
    "visual_coherence": 0.9456
  },
  "previous_count": 10,
  "avg_previous_topology_score": 0.9302,
  "avg_previous_visual_coherence": 0.9524,
  "avg_previous_overall_organ_coherence": 0.9524,
  "coherence_delta": -0.0068,
  "improvement": "neutral",
  "delta_trend": {
    "status": "stable_plateau",
    "rolling_3_delta": 0.0007,
    "previous_window": [
      0.9434,
      0.9425,
      0.9425
    ],
    "latest_window": [
      0.9425,
      0.9425,
      0.9456
    ],
    "reading": "Rolling 3-cycle trend is stable_plateau."
  },
  "live_route_protected": true,
  "top3": [
    {
      "key": "continue_visual_comparison",
      "title": "Continue visual comparison",
      "why": "The organ is stable but not clearly accelerating yet.",
      "recommended_patch": "Collect more visual entries before patching.",
      "severity": 0.4
    },
    {
      "key": "compare_visual_differences",
      "title": "Add visual difference descriptions",
      "why": "The organ is high-coherence and plateauing, so the next gain is describing what changed between SVGs.",
      "recommended_patch": "Add a sidecar that compares latest SVG/spec against previous SVG/spec and names the visible change.",
      "severity": 0.35
    }
  ],
  "surface_fragment": "Deepened visual judgment: improvement=neutral, coherence_delta=-0.0068, overall_organ_coherence=0.9456, trend=stable_plateau.",
  "law": "visual_judgment_is_deepened_append_only_and_helm_steering",
  "judge_sha256": "143d759c118a9a31"
}

